CHANGELOG.md
LICENSE
MANIFEST.in
README.md
setup.py
jsonrpcserver/__init__.py
jsonrpcserver/async_dispatcher.py
jsonrpcserver/dispatcher.py
jsonrpcserver/exceptions.py
jsonrpcserver/log.py
jsonrpcserver/methods.py
jsonrpcserver/request-schema.json
jsonrpcserver/request.py
jsonrpcserver/response.py
jsonrpcserver/server.py
jsonrpcserver/status.py
jsonrpcserver.egg-info/PKG-INFO
jsonrpcserver.egg-info/SOURCES.txt
jsonrpcserver.egg-info/dependency_links.txt
jsonrpcserver.egg-info/not-zip-safe
jsonrpcserver.egg-info/requires.txt
jsonrpcserver.egg-info/top_level.txt