Metadata-Version: 2.1
Name: jsonrpcserver
Version: 4.1.2
Summary: Process JSON-RPC requests
Home-page: https://github.com/bcb/jsonrpcserver
Author: Beau Barker
Author-email: beauinmelbourne@gmail.com
License: MIT
Platform: UNKNOWN
Classifier: Programming Language :: Python :: 3.6
Classifier: Programming Language :: Python :: 3.7
Classifier: Programming Language :: Python :: 3.8
Provides-Extra: tox
Provides-Extra: examples
